{
  "letter_spacing": "normal", 
  "vspace": "74", 
  "form_action": "/IntegriScreenServer/MainServer", 
  "ratio": "12:14", 
  "fontsize": "14pt", 
  "border_thickness": "1", 
  "page_id": "Random_35", 
  "font_family": "\"Arial\", sans-serif", 
  "elements": [
    {
      "width": "50", 
      "initialvalue": "Random 35", 
      "editable": "false", 
      "height": "15", 
      "type": "title", 
      "id": "form_title", 
      "ulc_x": "5", 
      "ulc_y": "2"
    }, 
    {
      "width": "27", 
      "initialvalue": "quietens", 
      "editable": "false", 
      "height": "9", 
      "type": "label", 
      "id": "0", 
      "ulc_x": "1.8", 
      "ulc_y": "19"
    }, 
    {
      "width": "37", 
      "initialvalue": "smirks", 
      "editable": "true", 
      "height": "9", 
      "type": "textfield", 
      "id": "1", 
      "ulc_x": "61.8", 
      "ulc_y": "19"
    }, 
    {
      "width": "37", 
      "initialvalue": "harden", 
      "editable": "true", 
      "height": "9", 
      "type": "textfield", 
      "id": "2", 
      "ulc_x": "41.8", 
      "ulc_y": "39"
    }, 
    {
      "width": "17", 
      "initialvalue": "dung", 
      "editable": "false", 
      "height": "9", 
      "type": "label", 
      "id": "3", 
      "ulc_x": "81.8", 
      "ulc_y": "39"
    }, 
    {
      "width": "87", 
      "initialvalue": "potty", 
      "editable": "false", 
      "height": "9", 
      "type": "button", 
      "id": "4", 
      "ulc_x": "1.8", 
      "ulc_y": "49"
    }, 
    {
      "width": "67", 
      "initialvalue": "broils", 
      "editable": "true", 
      "height": "9", 
      "type": "textfield", 
      "id": "5", 
      "ulc_x": "1.8", 
      "ulc_y": "59"
    }, 
    {
      "width": "17", 
      "initialvalue": "pond", 
      "editable": "true", 
      "height": "9", 
      "type": "textarea", 
      "id": "6", 
      "ulc_x": "81.8", 
      "ulc_y": "59"
    }, 
    {
      "width": "27", 
      "initialvalue": "sawmills", 
      "editable": "true", 
      "height": "9", 
      "type": "textfield", 
      "id": "7", 
      "ulc_x": "1.8", 
      "ulc_y": "69"
    }, 
    {
      "width": "17", 
      "initialvalue": "ford", 
      "editable": "true", 
      "height": "9", 
      "type": "textarea", 
      "id": "8", 
      "ulc_x": "61.8", 
      "ulc_y": "69"
    }, 
    {
      "width": "87", 
      "initialvalue": "distally", 
      "editable": "true", 
      "height": "9", 
      "type": "textfield", 
      "id": "9", 
      "ulc_x": "1.8", 
      "ulc_y": "89"
    }
  ]
}