{
  "letter_spacing": "normal", 
  "vspace": "72", 
  "form_action": "/IntegriScreenServer/MainServer", 
  "ratio": "13:12", 
  "fontsize": 12, 
  "border_thickness": "1", 
  "page_id": "Random_31", 
  "font_family": "\"Arial, sans-serif", 
  "elements": [
    {
      "width": "50", 
      "initialvalue": "Random 31", 
      "editable": "false", 
      "height": "9", 
      "type": "title", 
      "id": "form_title", 
      "ulc_x": "5", 
      "ulc_y": "2"
    }, 
    {
      "width": "67", 
      "initialvalue": "hackneying", 
      "editable": "false", 
      "height": "9", 
      "type": "label", 
      "id": "0", 
      "ulc_x": "1.8", 
      "ulc_y": "9"
    }, 
    {
      "width": "17", 
      "initialvalue": "brae", 
      "editable": "true", 
      "height": "9", 
      "type": "textarea", 
      "id": "1", 
      "ulc_x": "41.8", 
      "ulc_y": "29"
    }, 
    {
      "width": "37", 
      "initialvalue": "carnival", 
      "editable": "true", 
      "height": "9", 
      "type": "textarea", 
      "id": "2", 
      "ulc_x": "61.8", 
      "ulc_y": "29"
    }, 
    {
      "width": "57", 
      "initialvalue": "untenanted", 
      "editable": "false", 
      "height": "9", 
      "type": "label", 
      "id": "3", 
      "ulc_x": "41.8", 
      "ulc_y": "39"
    }, 
    {
      "width": "37", 
      "initialvalue": "meetup", 
      "editable": "false", 
      "height": "9", 
      "type": "label", 
      "id": "4", 
      "ulc_x": "41.8", 
      "ulc_y": "59"
    }, 
    {
      "width": "17", 
      "initialvalue": "jugs", 
      "editable": "false", 
      "height": "9", 
      "type": "button", 
      "id": "5", 
      "ulc_x": "81.8", 
      "ulc_y": "59"
    }, 
    {
      "width": "47", 
      "initialvalue": "gazer", 
      "editable": "true", 
      "height": "9", 
      "type": "textarea", 
      "id": "6", 
      "ulc_x": "1.8", 
      "ulc_y": "79"
    }, 
    {
      "width": "37", 
      "initialvalue": "barring", 
      "editable": "true", 
      "height": "9", 
      "type": "textfield", 
      "id": "7", 
      "ulc_x": "61.8", 
      "ulc_y": "89"
    }
  ]
}